psa_ccc/__init__.py
psa_ccc/apk_parser.py
psa_ccc/auth.py
psa_ccc/brand_config.py
psa_ccc/client.py
psa_ccc/github.py
psa_ccc/memory_token_storage.py
psa_ccc/models.py
psa_ccc/storage.py
psa_connected_car_client-0.1.1.dist-info/METADATA
psa_connected_car_client-0.1.1.dist-info/WHEEL
psa_connected_car_client-0.1.1.dist-info/RECORD
