Metadata-Version: 2.1
Name: psa-connected-car-client
Version: 0.1.1
Summary: 
Author: Andrea Ghensi
Author-email: andrea.ghensi@gmail.com
Requires-Python: >=3.10,<4.0
Classifier: Programming Language :: Python :: 3
Classifier: Programming Language :: Python :: 3.10
Classifier: Programming Language :: Python :: 3.11
Requires-Dist: authlib (>=1.2.0,<2.0.0)
Requires-Dist: cryptography (>=41.0.2,<42.0.0)
Requires-Dist: httpx (>=0.24.1,<0.25.0)
Requires-Dist: msgspec (>=0.18.2,<0.19.0)
Requires-Dist: pyaxmlparser (>=0.3.28,<0.4.0)
